Workbook

Sheet Calculator
A1: MESHNET pricing calculator
A2: Blue cells on yellow are inputs: edit these. Black cells are formulas. The values shown are EXAMPLES chosen by me, not real prices: replace them with your own. Use one currency throughout.
A4: Inputs | B4: Value | C4: Notes and assumptions
A5: Carrier price per GB (currency units) | B5: 1000 | C5: Example. Replace with what gateway owners really pay their carrier per GB.
A6: MB per GB | B6: 1024 | C6: Use 1000 if your carrier bills that way.
A7: Extra data used by the mesh on the gateway | B7: 0.1 | C7: Assumption: encryption, headers and retransmissions add data. Measure this in the pilot.
A8: Target gateway profit over its data cost | B8: 0.3 | C8: Your choice: how much the gateway should earn above its own data cost.
A9: Price of ONE credit (currency units) | B9: 1 | C9: You set this: what a user pays to buy one credit.
A10: Price per MB charged to the receiver (credits) | B10: 3 | C10: You set this. Example value.
A11: Gateway share of each payment | B11: 0.5 | C11: Example split from the project (50/40/10).
A12: Relays share (total, split among hops) | B12: 0.4 | C12: Example split from the project.
A13: Platform share (the remainder) | B13: =1-B11-B12 -> 0.1 | C13: Formula: 100% minus gateway and relays.
A14: Relay hops on a typical path | B14: 2 | C14: Example. The pilot will show the real average.
A16: Results (per MB) | B16: Value | C16: How it is worked out
A17: Gateway's carrier data cost per user MB | B17: =B5/B6*(1+B7) -> 1.0742188 | C17: Carrier price per MB, plus the mesh overhead.
A18: Receiver pays per MB (currency) | B18: =B9*B10 -> 3 | C18: Credit price x credits per MB.
A19: Gateway earns per MB | B19: =B18*B11 -> 1.5 | C19: Receiver payment x gateway share.
A20: Gateway profit per MB | B20: =B19-B17 -> 0.42578125 | C20: Earnings minus its data cost. Negative means the gateway loses money.
A21: Gateway profit over its data cost | B21: =IF(B17>0,B20/B17,0) -> 0.39636364 | C21: Compare with the target above.
A22: Each relay earns per MB | B22: =IF(B14>0,B18*B12/B14,0) -> 0.6 | C22: Relay pool divided by the number of hops.
A23: Platform earns per MB | B23: =B18*B13 -> 0.3 | C23: Receiver payment x platform share.
A24: Receiver pays per GB (currency) | B24: =B18*B6 -> 3072 | C24: What a heavy user would see.
A25: Compared with a direct carrier GB | B25: =IF(B5>0,B24/B5,0) -> 3.072 | C25: How many times more than the carrier price. A large number may put users off.
A27: Checks | B27: Value | C27: What it tells you
A28: Lowest price per MB (credits) that meets the target | B28: =IF(AND(B9>0,B11>0),B17*(1+B8)/B11/B9,0) -> 2.7929688 | C28: At your credit price and gateway share.
A29: Lowest gateway share that meets the target | B29: =IF(B18>0,B17*(1+B8)/B18,0) -> 0.46549479 | C29: At your current price per MB.
A30: Gateway verdict | B30: =IF(B21>=B8,"Gateway meets the target","Gateway is below target: raise the price or its share") -> Gateway meets the target
A31: Split check | B31: =IF(B13>=0,"Shares add up correctly","Shares add up to more than 100%: lower them") -> Shares add up correctly

Sheet Scenarios
A1: Compare prices per MB
A2: Change the blue credits-per-MB values in column A. Everything else uses the inputs on the Calculator sheet.
A4: Price per MB (credits) | B4: Receiver pays per MB | C4: Gateway profit per MB | D4: Gateway profit over cost | E4: Each relay earns per MB | F4: Receiver pays per GB | G4: x direct carrier GB | H4: Gateway status
A5: 1 | B5: =Calculator!$B$9*A5 -> 1 | C5: =B5*Calculator!$B$11-Calculator!$B$17 -> -0.57421875 | D5: =IF(Calculator!$B$17>0,C5/Calculator!$B$17,0) -> -0.53454545 | E5: =IF(Calculator!$B$14>0,B5*Calculator!$B$12/Calculator!$B$14,0) -> 0.2 | F5: =B5*Calculator!$B$6 -> 1024 | G5: =IF(Calculator!$B$5>0,F5/Calculator!$B$5,0) -> 1.024 | H5: =IF(D5>=Calculator!$B$8,"Meets target","Below target") -> Below target
A6: 2 | B6: =Calculator!$B$9*A6 -> 2 | C6: =B6*Calculator!$B$11-Calculator!$B$17 -> -0.07421875 | D6: =IF(Calculator!$B$17>0,C6/Calculator!$B$17,0) -> -0.069090909 | E6: =IF(Calculator!$B$14>0,B6*Calculator!$B$12/Calculator!$B$14,0) -> 0.4 | F6: =B6*Calculator!$B$6 -> 2048 | G6: =IF(Calculator!$B$5>0,F6/Calculator!$B$5,0) -> 2.048 | H6: =IF(D6>=Calculator!$B$8,"Meets target","Below target") -> Below target
A7: 3 | B7: =Calculator!$B$9*A7 -> 3 | C7: =B7*Calculator!$B$11-Calculator!$B$17 -> 0.42578125 | D7: =IF(Calculator!$B$17>0,C7/Calculator!$B$17,0) -> 0.39636364 | E7: =IF(Calculator!$B$14>0,B7*Calculator!$B$12/Calculator!$B$14,0) -> 0.6 | F7: =B7*Calculator!$B$6 -> 3072 | G7: =IF(Calculator!$B$5>0,F7/Calculator!$B$5,0) -> 3.072 | H7: =IF(D7>=Calculator!$B$8,"Meets target","Below target") -> Meets target
A8: 4 | B8: =Calculator!$B$9*A8 -> 4 | C8: =B8*Calculator!$B$11-Calculator!$B$17 -> 0.92578125 | D8: =IF(Calculator!$B$17>0,C8/Calculator!$B$17,0) -> 0.86181818 | E8: =IF(Calculator!$B$14>0,B8*Calculator!$B$12/Calculator!$B$14,0) -> 0.8 | F8: =B8*Calculator!$B$6 -> 4096 | G8: =IF(Calculator!$B$5>0,F8/Calculator!$B$5,0) -> 4.096 | H8: =IF(D8>=Calculator!$B$8,"Meets target","Below target") -> Meets target
A9: 5 | B9: =Calculator!$B$9*A9 -> 5 | C9: =B9*Calculator!$B$11-Calculator!$B$17 -> 1.4257812 | D9: =IF(Calculator!$B$17>0,C9/Calculator!$B$17,0) -> 1.3272727 | E9: =IF(Calculator!$B$14>0,B9*Calculator!$B$12/Calculator!$B$14,0) -> 1 | F9: =B9*Calculator!$B$6 -> 5120 | G9: =IF(Calculator!$B$5>0,F9/Calculator!$B$5,0) -> 5.12 | H9: =IF(D9>=Calculator!$B$8,"Meets target","Below target") -> Meets target

Sheet Notes
A1: Notes and assumptions
A2: Read before relying on the numbers.
A4: 1. All numbers on the Calculator sheet are placeholders chosen by me for illustration. None are real market prices.
A5: 2. You, as the operator, set two separate prices: what one credit costs a user in real currency, and how many credits one MB costs. The receiver pays their product.
A6: 3. The gateway's data cost uses its carrier price per GB. The mesh adds overhead (assumed 10%), so the gateway uses more data than the user sees.
A7: 4. Relays and hops are paid from the relay share only. Their real cost is battery, which this sheet does not price: check relays earn enough to be willing.
A8: 5. The receiver compares MESHNET with their own carrier price per GB. Check the "x direct carrier GB" figure is acceptable for people with a weak signal.
A9: 6. Fees from payment providers, taxes and refunds are not included.
A10: 7. If credits can be turned back into cash, payment or e-money rules may apply where you operate. Get legal advice before launching real payments.
A11: 8. Some carriers restrict sharing or reselling data. Check the terms that gateway owners are bound by.
